mega_drive_storage/__init__.py
mega_drive_storage/_mega.py
mega_drive_storage/apps.py
mega_drive_storage/storage.py
mega_drive_storage/tests.py
django_mega_drive_storage-0.2.dist-info/LICENSE
django_mega_drive_storage-0.2.dist-info/METADATA
django_mega_drive_storage-0.2.dist-info/WHEEL
django_mega_drive_storage-0.2.dist-info/top_level.txt
django_mega_drive_storage-0.2.dist-info/RECORD
