Metadata-Version: 2.1
Name: django-mega-drive-storage
Version: 0.2
Summary: A simple storage for uploading files to mega-drive cloud.
Home-page: UNKNOWN
Author: Rahul Singh
Author-email: rahulsingh32929@gmail.com
License: MIT
Keywords: django-mega-drive-storage djang-mega drive-storage django_mega django_mega_drive mega_drive mega mega_python
Platform: UNKNOWN
License-File: LICENSE
Requires-Dist: django
Requires-Dist: mega.py
